nowpay/__init__.py
nowpay/ipn.py
nowpay-2.1.0.dist-info/LICENSE
nowpay-2.1.0.dist-info/METADATA
nowpay-2.1.0.dist-info/WHEEL
nowpay-2.1.0.dist-info/top_level.txt
nowpay-2.1.0.dist-info/RECORD
