Metadata-Version: 2.1
Name: nowpay
Version: 2.1.0
Summary: NOWPayments python API
Home-page: https://github.com/NikolaiSch/NowPay-Python
Author: @NikolaiSch
Author-email: NikolaiS@tuta.io
License: UNKNOWN
Project-URL: Bug Tracker, https://github.com/NikolaiSch/NowPay-Python/issues
Platform: UNKNOWN
Classifier: Programming Language :: Python :: 3
Classifier: License :: OSI Approved :: MIT License
Classifier: Operating System :: OS Independent
Requires-Python: >=3.6
License-File: LICENSE
